h/__init__.py
h/_session.py
h/_utils.py
h/exceptions.py
h/models.py
h/_async/__init__.py
h/_async/connection.py
h/_async/connection_pool.py
h/_backend/__init__.py
h/_backend/async_.py
h/_backend/sync.py
h-0.99.dist-info/LICENSE
h-0.99.dist-info/WHEEL
h-0.99.dist-info/METADATA
h-0.99.dist-info/RECORD
