Metadata-Version: 1.1
Name: h
Version: 0.99
Summary: Temporary upload
Home-page: https://github.com/sethmlarson/h
Author: Seth Michael Larson
Author-email: sethmichaellarson@gmail.com
